pop_doc/conf.py
pop_doc/scripts.py
pop_tree/conf.py
pop_tree/scripts.py
pop_tree/graph/init.py
pop_tree/graph/networkx.py
pop_tree/graph/text_details.py
pop_tree/graph/text_json.py
pop_tree/graph/text_simple.py
pop_tree/graph/contracts/init.py
pop_tree/graph/contracts/networkx.py
pop_tree/tree/init.py
pop_tree/tree/mod.py
pop_tree/tree/ref.py
pop_tree/tree/sub.py
pop_tree-12.1.2.dist-info/LICENSE
pop_tree-12.1.2.dist-info/METADATA
pop_tree-12.1.2.dist-info/WHEEL
pop_tree-12.1.2.dist-info/entry_points.txt
pop_tree-12.1.2.dist-info/top_level.txt
pop_tree-12.1.2.dist-info/RECORD
