Metadata-Version: 2.1
Name: pop-tree
Version: 12.1.2
Summary: Visualize POP hub/sub structures
Home-page: https://vmware.gitlab.io/pop/pop-tree/en/latest/index.html
Author: VMware, Inc.
Author-email: idemproject@vmware.com
License: Apache Software License 2.0
Project-URL: Code, https://gitlab.com/vmware/pop/pop-tree
Project-URL: Issue tracker, https://gitlab.com/vmware/pop/pop-tree/issues
Classifier: Environment :: Console
Classifier: Intended Audience :: Developers
Classifier: Intended Audience :: Information Technology
Classifier: Intended Audience :: System Administrators
Classifier: Operating System :: OS Independent
Classifier: Programming Language :: Python
Classifier: Programming Language :: Python :: 3.8
Classifier: Programming Language :: Python :: 3.9
Classifier: Programming Language :: Python :: 3.10
Classifier: Programming Language :: Python :: 3.11
Classifier: Development Status :: 5 - Production/Stable
Classifier: License :: OSI Approved :: Apache Software License
Requires-Python: >=3.8
License-File: LICENSE
Requires-Dist: aiofiles
Requires-Dist: pop >=26.0.0
Requires-Dist: dict-toolbox >=3.1.0
Requires-Dist: rend
Requires-Dist: docstring-parser >=0.15
Provides-Extra: full
Requires-Dist: pyqt5 ; extra == 'full'
Requires-Dist: matplotlib ; extra == 'full'
Requires-Dist: scipy ; extra == 'full'
Requires-Dist: networkx ; extra == 'full'
Provides-Extra: networkx
Requires-Dist: networkx ; extra == 'networkx'
Requires-Dist: scipy ; extra == 'networkx'
Requires-Dist: matplotlib ; extra == 'networkx'
Requires-Dist: pyqt5 ; extra == 'networkx'
